supervised_FCN_2/__init__.py
supervised_FCN_2/example_compute_FID.py
supervised_FCN_2/example_compute_IS.py
supervised_FCN_2/example_data_loading.py
supervised_FCN_2/example_pretrained_model_loading.py
supervised_FCN_2/train_fcn.py
supervised_FCN_2/train_fcn_all_datasets.py
supervised_FCN_2/datasets/DataSummary_UCR.csv
supervised_FCN_2/datasets/__init__.py
supervised_FCN_2/experiments/__init__.py
supervised_FCN_2/experiments/exp_base.py
supervised_FCN_2/experiments/exp_train.py
supervised_FCN_2/models/__init__.py
supervised_FCN_2/models/fcn.py
supervised_FCN_2/preprocessing/__init__.py
supervised_FCN_2/preprocessing/augmentations.py
supervised_FCN_2/preprocessing/data_pipeline.py
supervised_FCN_2/preprocessing/preprocess_ucr.py
supervised_FCN_2/preprocessing/preprocess_uea.py
supervised_FCN_2/saved_models/__init__.py
supervised_FCN_2/utils/__init__.py
supervised_fcn_2-0.0.4.dist-info/LICENSE
supervised_fcn_2-0.0.4.dist-info/METADATA
supervised_fcn_2-0.0.4.dist-info/WHEEL
supervised_fcn_2-0.0.4.dist-info/top_level.txt
supervised_fcn_2-0.0.4.dist-info/RECORD
